the_rover/__init__.py
the_rover/__main__.py
the_rover-1.0.2.dist-info/LICENSE.txt
the_rover-1.0.2.dist-info/METADATA
the_rover-1.0.2.dist-info/WHEEL
the_rover-1.0.2.dist-info/entry_points.txt
the_rover-1.0.2.dist-info/top_level.txt
the_rover-1.0.2.dist-info/RECORD
