Metadata-Version: 2.1
Name: the-rover
Version: 1.0.2
Summary: THE rover. Allows controlling Raspberry Pi "rovers" remotely and interactively from any OS's command line.
Author-email: Medhansh Choudhury <sondad2008@gmail.com>
Maintainer-email: Medhansh Choudhury <sondad2008@gmail.com>, Alex Bace <alexbace2@gmail.com>
License: GNU Affero General Public License v3.0
Project-URL: Homepage, https://https://github.com/xboxone08/the_rover
Project-URL: Documentation, https://github.com/xboxone08/the_rover/blob/main/README.md
Project-URL: Issues, https://github.com/xboxone08/the_rover/issues
Project-URL: Releases, https://github.com/xboxone08/the_rover/releases
Keywords: the_rover,the-rover,rover
Classifier: Development Status :: 5 - Production/Stable
Classifier: Environment :: Console
Classifier: License :: OSI Approved :: GNU Affero General Public License v3
Classifier: Natural Language :: English
Classifier: Programming Language :: Python :: 3 :: Only
Classifier: Operating System :: OS Independent
Requires-Python: >=3.0.0
License-File: LICENSE.txt
Requires-Dist: gpiozero
Requires-Dist: pigpio
Requires-Dist: keyboard
Requires-Dist: fabric
